server/__init__.py
server/main.py
server/mcp.py
yuanqiservermickal-1.0.1.dist-info/METADATA
yuanqiservermickal-1.0.1.dist-info/WHEEL
yuanqiservermickal-1.0.1.dist-info/top_level.txt
yuanqiservermickal-1.0.1.dist-info/RECORD
