Metadata-Version: 2.2
Name: yuanqiservermickal
Version: 1.0.1
Summary: A mcp server
Author: yuanqi_mcp163
Author-email: yuanqi_mcp_test@163.com
License: MIT
Requires-Python: >=3.12
Requires-Dist: mcp
Requires-Dist: httpx
Requires-Dist: uvicorn
Dynamic: author
Dynamic: author-email
Dynamic: license
Dynamic: requires-dist
Dynamic: requires-python
Dynamic: summary
